pyjisa/__init__.py
pyjisa/autoload.py
pyjisa-1.4.dist-info/METADATA
pyjisa-1.4.dist-info/WHEEL
pyjisa-1.4.dist-info/top_level.txt
pyjisa-1.4.dist-info/RECORD
